[
    {
        "id": "21",
        "nombre": "WEB ECOMMERCE INCIAL",
        "descripcion": "Web Ecommerce Inicial, Sitio optimizado y diseñado con WordPress.",
        "correo": "Cuentas de Correo Electronico con la extension de su dominio",
        "dominio": "Cuenta con Dominio .com.ar",
        "hosting": "Cuenta con Hosting Premium",
        "responsive": "Sitio Responsive: Adaptable a todos los dispositivos",
        "ssl": "El sitio cuenta con Certificacion SSL (Seguridad para tus clientes)",
        "formulario": "Formulario de Contacto",
        "mapa": "Mapa de Ubicacion del Local/Emprendimiento",
        "wsp": "Boton de WhatsApp Integrado en Sitio",
        "woo": "Cuenta con Servicio WooCommerce",
        "Pasarela": "Pasarelas de Pago: Mercado Pago, Uala, MODO, Cuenta DNI, Etc...",
        "nocomi": "El servicio no cobra comision por ventas realizadas",
        "productos": "El servicio incial cuenta con 10 productos iniciales",
        "section": "Cuenta con hasta 4 secciones, adicionales por cotizacion",
        "seo": "Sitio con Optimizacion SEO para buscadores",
        "img": "./images/ecommerce.png",
        "precio": 100000
    },
    {
        "id": "22",
        "nombre": "WEB ECOMMERCE INTERMEDIO",
        "descripcion": "Web Ecommerce Intermedio Sitio optimizado y diseñado con WordPress.",
        "correo": "Cuentas de Correo Electronico con la extension de su dominio",
        "dominio": "Cuenta con Dominio .com.ar",
        "hosting": "Cuenta con Hosting Premium con Copias de Seguridad Diarias",
        "responsive": "Sitio Responsive: Adaptable a todos los dispositivos",
        "ssl": "El sitio cuenta con Certificacion SSL (Seguridad para tus clientes)",
        "formulario": "Formulario de Contacto",
        "mapa": "Mapa de Ubicacion del Local/Emprendimiento",
        "wsp": "Boton de WhatsApp Integrado en Sitio",
        "woo": "Cuenta con Servicio WooCommerce",
        "Pasarela": "Pasarelas de Pago: Mercado Pago, Uala, MODO, Cuenta DNI, Etc...",
        "nocomi": "El servicio no cobra comision por ventas realizadas",
        "productos": "El servicio intermedio cuenta con 50 productos",
        "section": "Cuenta con hasta 5 secciones, adicionales por cotizacion",
        "seo": "Sitio con Optimizacion SEO para buscadores",
        "img": "./images/ecommerceint.png",
        "precio": 175000
    },
    {
        "id": "23",
        "nombre": "WEB ECOMMERCE AVANZADO",
        "descripcion": "Web Ecommerce Intermedio Sitio optimizado y diseñado con WordPress.",
        "correo": "Cuentas de Correo Electronico con la extension de su dominio",
        "dominio": "Cuenta con Dominio .com.ar",
        "hosting": "Cuenta con Hosting Premium con Copias de Seguridad Diarias",
        "responsive": "Sitio Responsive: Adaptable a todos los dispositivos",
        "ssl": "El sitio cuenta con Certificacion SSL (Seguridad para tus clientes)",
        "formulario": "Formulario de Contacto",
        "mapa": "Mapa de Ubicacion del Local/Emprendimiento",
        "wsp": "Boton de WhatsApp Integrado en Sitio",
        "woo": "Cuenta con Servicio WooCommerce",
        "Pasarela": "Pasarelas de Pago: Mercado Pago, Uala, MODO, Cuenta DNI, Etc...",
        "nocomi": "El servicio no cobra comision por ventas realizadas",
        "productos": "El servicio avanzado cuenta con 100+ productos",
        "section": "Cuenta con hasta 4 secciones, adicionales por cotizacion",
        "seo": "Sitio con Optimizacion SEO para buscadores",
        "img": "./images/ecommerceavan.png",
        "precio": 250000
    },
    {
        "id": "24",
        "nombre": "WEB ECOMMERCE COMPLETO",
        "descripcion": "Web Ecommerce Intermedio Sitio optimizado y diseñado con WordPress.",
        "correo": "Cuentas de Correo Electronico con la extension de su dominio",
        "dominio": "Cuenta con Dominio .com.ar",
        "hosting": "Cuenta con Hosting Premium con Copias de Seguridad Diarias",
        "responsive": "Sitio Responsive: Adaptable a todos los dispositivos",
        "ssl": "El sitio cuenta con Certificacion SSL (Seguridad para tus clientes)",
        "formulario": "Formulario de Contacto",
        "mapa": "Mapa de Ubicacion del Local/Emprendimiento",
        "wsp": "Boton de WhatsApp Integrado en Sitio",
        "woo": "Cuenta con Servicio WooCommerce",
        "Pasarela": "Pasarelas de Pago: Mercado Pago, Uala, MODO, Cuenta DNI, Etc...",
        "nocomi": "El servicio no cobra comision por ventas realizadas",
        "productos": "El servicio avanzado cuenta con 100+ productos",
        "section": "Cuenta con hasta 4 secciones, adicionales por cotizacion",
        "seo": "Sitio con Optimizacion SEO para buscadores",
        "img": "./images/ecommerceavan.png",
        "precio": 250000
    },
    {
        "id": "25",
        "nombre": "WEB ECOMMERCE INFORMATICA",
        "descripcion": "Web Ecommerce Intermedio Sitio optimizado y diseñado con WordPress.",
        "correo": "Cuentas de Correo Electronico con la extension de su dominio",
        "dominio": "Cuenta con Dominio .com.ar",
        "hosting": "Cuenta con Hosting Premium con Copias de Seguridad Diarias",
        "responsive": "Sitio Responsive: Adaptable a todos los dispositivos",
        "ssl": "El sitio cuenta con Certificacion SSL (Seguridad para tus clientes)",
        "formulario": "Formulario de Contacto",
        "mapa": "Mapa de Ubicacion del Local/Emprendimiento",
        "wsp": "Boton de WhatsApp Integrado en Sitio",
        "woo": "Cuenta con Servicio WooCommerce",
        "Pasarela": "Pasarelas de Pago: Mercado Pago, Uala, MODO, Cuenta DNI, Etc...",
        "nocomi": "El servicio no cobra comision por ventas realizadas",
        "productos": "El servicio avanzado cuenta con 100+ productos",
        "section": "Cuenta con hasta 4 secciones, adicionales por cotizacion",
        "seo": "Sitio con Optimizacion SEO para buscadores",
        "img": "./images/ecommerceavan.png",
        "precio": 250000
    },
    {
        "id": "26",
        "nombre": "WEB ECOMMERCE PYME",
        "descripcion": "Web Ecommerce Intermedio Sitio optimizado y diseñado con WordPress.",
        "correo": "Cuentas de Correo Electronico con la extension de su dominio",
        "dominio": "Cuenta con Dominio .com.ar",
        "hosting": "Cuenta con Hosting Premium con Copias de Seguridad Diarias",
        "responsive": "Sitio Responsive: Adaptable a todos los dispositivos",
        "ssl": "El sitio cuenta con Certificacion SSL (Seguridad para tus clientes)",
        "formulario": "Formulario de Contacto",
        "mapa": "Mapa de Ubicacion del Local/Emprendimiento",
        "wsp": "Boton de WhatsApp Integrado en Sitio",
        "woo": "Cuenta con Servicio WooCommerce",
        "Pasarela": "Pasarelas de Pago: Mercado Pago, Uala, MODO, Cuenta DNI, Etc...",
        "nocomi": "El servicio no cobra comision por ventas realizadas",
        "productos": "El servicio avanzado cuenta con 100+ productos",
        "section": "Cuenta con hasta 4 secciones, adicionales por cotizacion",
        "seo": "Sitio con Optimizacion SEO para buscadores",
        "img": "./images/ecommerceavan.png",
        "precio": 250000
    },
    {
        "id": "27",
        "img": "./images/ecommerceavan.png",
        "nombre": "WEB ECOMMERCE AUTONOMO",
        "descripcion": "Web Ecommerce Intermedio Sitio optimizado y diseñado con WordPress.",
        "correo": "Cuentas de Correo Electronico con la extension de su dominio",
        "dominio": "Cuenta con Dominio .com.ar",
        "hosting": "Cuenta con Hosting Premium con Copias de Seguridad Diarias",
        "ssl": "El sitio cuenta con Certificacion SSL (Seguridad para tus clientes)",
        "responsive": "Sitio Responsive: Adaptable a todos los dispositivos",
        "mapa": "Mapa de Ubicacion del Local/Emprendimiento",
        "wsp": "Boton de WhatsApp Integrado en Sitio",
        "seo": "Sitio con Optimizacion SEO para buscadores",
        "formulario": "Formulario de Contacto",
        "woo": "Cuenta con Servicio WooCommerce",
        "Pasarela": "Pasarelas de Pago: Mercado Pago, Uala, MODO, Cuenta DNI, Etc...",
        "nocomi": "El servicio no cobra comision por ventas realizadas",
        "productos": "El servicio avanzado cuenta con 100+ productos",
        "section": "Cuenta con hasta 4 secciones, adicionales por cotizacion",
        "precio": 250000
    },
    {
        "id": "28",
        "nombre": "WEB ECOMMERCE ",
        "descripcion": "Web Ecommerce Intermedio Sitio optimizado y diseñado con WordPress.",
        "correo": "Cuentas de Correo Electronico con la extension de su dominio",
        "dominio": "Cuenta con Dominio .com.ar",
        "hosting": "Cuenta con Hosting Premium con Copias de Seguridad Diarias",
        "responsive": "Sitio Responsive: Adaptable a todos los dispositivos",
        "ssl": "El sitio cuenta con Certificacion SSL (Seguridad para tus clientes)",
        "formulario": "Formulario de Contacto",
        "mapa": "Mapa de Ubicacion del Local/Emprendimiento",
        "wsp": "Boton de WhatsApp Integrado en Sitio",
        "woo": "Cuenta con Servicio WooCommerce",
        "Pasarela": "Pasarelas de Pago: Mercado Pago, Uala, MODO, Cuenta DNI, Etc...",
        "nocomi": "El servicio no cobra comision por ventas realizadas",
        "productos": "El servicio avanzado cuenta con 100+ productos",
        "section": "Cuenta con hasta 4 secciones, adicionales por cotizacion",
        "seo": "Sitio con Optimizacion SEO para buscadores",
        "img": "./images/ecommerceavan.png",
        "precio": 250000
    },
    {
        "id": "29",
        "nombre": "WEB ECOMMERCE AVANZADO",
        "descripcion": "Web Ecommerce Intermedio Sitio optimizado y diseñado con WordPress.",
        "correo": "Cuentas de Correo Electronico con la extension de su dominio",
        "dominio": "Cuenta con Dominio .com.ar",
        "hosting": "Cuenta con Hosting Premium con Copias de Seguridad Diarias",
        "responsive": "Sitio Responsive: Adaptable a todos los dispositivos",
        "ssl": "El sitio cuenta con Certificacion SSL (Seguridad para tus clientes)",
        "formulario": "Formulario de Contacto",
        "mapa": "Mapa de Ubicacion del Local/Emprendimiento",
        "wsp": "Boton de WhatsApp Integrado en Sitio",
        "woo": "Cuenta con Servicio WooCommerce",
        "Pasarela": "Pasarelas de Pago: Mercado Pago, Uala, MODO, Cuenta DNI, Etc...",
        "nocomi": "El servicio no cobra comision por ventas realizadas",
        "productos": "El servicio avanzado cuenta con 100+ productos",
        "section": "Cuenta con hasta 4 secciones, adicionales por cotizacion",
        "seo": "Sitio con Optimizacion SEO para buscadores",
        "img": "./images/ecommerceavan.png",
        "precio": 250000
    },
    {
        "id": "30",
        "nombre": "WEB ECOMMERCE AVANZADO",
        "descripcion": "Web Ecommerce Intermedio Sitio optimizado y diseñado con WordPress.",
        "correo": "Cuentas de Correo Electronico con la extension de su dominio",
        "dominio": "Cuenta con Dominio .com.ar",
        "hosting": "Cuenta con Hosting Premium con Copias de Seguridad Diarias",
        "responsive": "Sitio Responsive: Adaptable a todos los dispositivos",
        "ssl": "El sitio cuenta con Certificacion SSL (Seguridad para tus clientes)",
        "formulario": "Formulario de Contacto",
        "mapa": "Mapa de Ubicacion del Local/Emprendimiento",
        "wsp": "Boton de WhatsApp Integrado en Sitio",
        "woo": "Cuenta con Servicio WooCommerce",
        "Pasarela": "Pasarelas de Pago: Mercado Pago, Uala, MODO, Cuenta DNI, Etc...",
        "nocomi": "El servicio no cobra comision por ventas realizadas",
        "productos": "El servicio avanzado cuenta con 100+ productos",
        "section": "Cuenta con hasta 4 secciones, adicionales por cotizacion",
        "seo": "Sitio con Optimizacion SEO para buscadores",
        "img": "./images/ecommerceavan.png",
        "precio": 250000
    },
    {
        "id": "31",
        "nombre": "WEB ECOMMERCE AVANZADO",
        "descripcion": "Web Ecommerce Intermedio Sitio optimizado y diseñado con WordPress.",
        "correo": "Cuentas de Correo Electronico con la extension de su dominio",
        "dominio": "Cuenta con Dominio .com.ar",
        "hosting": "Cuenta con Hosting Premium con Copias de Seguridad Diarias",
        "responsive": "Sitio Responsive: Adaptable a todos los dispositivos",
        "ssl": "El sitio cuenta con Certificacion SSL (Seguridad para tus clientes)",
        "formulario": "Formulario de Contacto",
        "mapa": "Mapa de Ubicacion del Local/Emprendimiento",
        "wsp": "Boton de WhatsApp Integrado en Sitio",
        "woo": "Cuenta con Servicio WooCommerce",
        "Pasarela": "Pasarelas de Pago: Mercado Pago, Uala, MODO, Cuenta DNI, Etc...",
        "nocomi": "El servicio no cobra comision por ventas realizadas",
        "productos": "El servicio avanzado cuenta con 100+ productos",
        "section": "Cuenta con hasta 4 secciones, adicionales por cotizacion",
        "seo": "Sitio con Optimizacion SEO para buscadores",
        "img": "./images/ecommerceavan.png",
        "precio": 250000
    }
]